pbrtool/__init__.py
pbrtool/cli.py
pbrtool/pbrtool.py
pbrtool/test.py
pbrtool-0.3.0.dist-info/AUTHORS
pbrtool-0.3.0.dist-info/METADATA
pbrtool-0.3.0.dist-info/WHEEL
pbrtool-0.3.0.dist-info/entry_points.txt
pbrtool-0.3.0.dist-info/pbr.json
pbrtool-0.3.0.dist-info/top_level.txt
pbrtool-0.3.0.dist-info/RECORD
