Metadata-Version: 2.1
Name: pbrtool
Version: 0.3.0
Summary: Python Pbr generate tool
Home-page: http://www.singein.com
Author: Singein
Author-email: Singein@outlook.com
License: MIT
Platform: UNKNOWN
Classifier: Development Status :: 4 - Beta
Classifier: Environment :: Console
Classifier: Environment :: OpenStack
Classifier: Intended Audience :: Developers
Classifier: Intended Audience :: Information Technology
Classifier: License :: OSI Approved :: Apache Software License
Classifier: Operating System :: OS Independent
Classifier: Programming Language :: Python
Requires-Dist: fire (==0.1.3)
Requires-Dist: osprofile
